wkmeans_geo/__init__.py
wkmeans_geo/clusters_from_input.py
wkmeans_geo/wkmeans_clustering.py
wkmeans_geo/src/__init__.py
wkmeans_geo/src/clusters.py
wkmeans_geo/src/data.py
wkmeans_geo/src/initiation.py
wkmeans_geo/src/optimization_model.py
cimren_wkmeans_geo-1.3.4.dist-info/METADATA
cimren_wkmeans_geo-1.3.4.dist-info/WHEEL
cimren_wkmeans_geo-1.3.4.dist-info/top_level.txt
cimren_wkmeans_geo-1.3.4.dist-info/RECORD
