Metadata-Version: 2.1
Name: cimren-wkmeans-geo
Version: 1.3.4
Summary: Weighted KMeans Clustering for Geolocational Problem
Home-page: https://github.com/emrahcimren/wkmeans-geo
Author: cimren
Author-email: cimren.1@gmail.com
License: MIT
Platform: UNKNOWN
Classifier: License :: OSI Approved :: MIT License
Classifier: Programming Language :: Python :: 3
Classifier: Programming Language :: Python :: 3.6
Requires-Dist: bleach (==3.1.0)
Requires-Dist: bumpversion (==0.5.3)
Requires-Dist: certifi (==2019.11.28)
Requires-Dist: chardet (==3.0.4)
Requires-Dist: cimren-helpers (==1.0.3)
Requires-Dist: docutils (==0.16)
Requires-Dist: Faker (==3.0.0)
Requires-Dist: feedparser (==5.2.1)
Requires-Dist: html2text (==2019.9.26)
Requires-Dist: idna (==2.8)
Requires-Dist: importlib-metadata (==1.4.0)
Requires-Dist: importlib-resources (==1.0.2)
Requires-Dist: keyring (==21.1.0)
Requires-Dist: more-itertools (==8.1.0)
Requires-Dist: numpy (==1.17.3)
Requires-Dist: ortools (==7.5.7466)
Requires-Dist: pandas (==0.25.3)
Requires-Dist: pathlib (==1.0.1)
Requires-Dist: pkginfo (==1.5.0.1)
Requires-Dist: plotly (==4.4.1)
Requires-Dist: protobuf (==3.11.2)
Requires-Dist: Pygments (==2.5.2)
Requires-Dist: python-dateutil (==2.8.1)
Requires-Dist: pytz (==2019.3)
Requires-Dist: pywin32-ctypes (==0.2.0)
Requires-Dist: readme-renderer (==24.0)
Requires-Dist: realpython-reader (==1.0.0)
Requires-Dist: requests (==2.22.0)
Requires-Dist: requests-toolbelt (==0.9.1)
Requires-Dist: retrying (==1.3.3)
Requires-Dist: six (==1.13.0)
Requires-Dist: text-unidecode (==1.3)
Requires-Dist: tqdm (==4.41.1)
Requires-Dist: twine (==3.1.1)
Requires-Dist: typing (==3.7.4.1)
Requires-Dist: urllib3 (==1.25.7)
Requires-Dist: webencodings (==0.5.1)
Requires-Dist: wincertstore (==0.2)
Requires-Dist: zipp (==1.0.0)
